{
  "league": "NBA",
  "default_strategy": "riskAdjusted",
  "strategy_configs": {
    "riskAdjusted": {
      "label": "Balanced",
      "shortLabel": "Standard risk",
      "allowUnderdogs": true,
      "minEdge": 0.03,
      "minExpectedValue": 0.02,
      "stakeScale": 0.5,
      "maxBetBankrollPercent": 1.25,
      "maxDailyBankrollPercent": 4,
      "description": "Balanced baseline with the shared value screen, a 1.25% per-bet cap, and a 4% nightly budget on the reference bankroll.",
      "config_signature": "bet_strategy_frontier_v1|dogs|0.030|0.020|0.500|1.250|4.000",
      "optimization_objective": "Static balanced default while matched replay coverage remains limited",
      "optimization_source": "static_fallback",
      "metrics": null
    },
    "aggressive": {
      "label": "Aggressive",
      "shortLabel": "Wider caps",
      "allowUnderdogs": true,
      "minEdge": 0.03,
      "minExpectedValue": 0.02,
      "stakeScale": 0.75,
      "maxBetBankrollPercent": 1.75,
      "maxDailyBankrollPercent": 6,
      "description": "Aggressive baseline with the shared value screen, a 1.75% per-bet cap, and a 6% nightly budget on the reference bankroll.",
      "config_signature": "bet_strategy_frontier_v1|dogs|0.030|0.020|0.750|1.750|6.000",
      "optimization_objective": "Static aggressive default while matched replay coverage remains limited",
      "optimization_source": "static_fallback",
      "metrics": null
    },
    "capitalPreservation": {
      "label": "Conservative",
      "shortLabel": "Favorites only",
      "allowUnderdogs": false,
      "minEdge": 0.03,
      "minExpectedValue": 0.02,
      "stakeScale": 0.25,
      "maxBetBankrollPercent": 0.75,
      "maxDailyBankrollPercent": 2.5,
      "description": "Conservative baseline with the shared value screen, a 0.75% per-bet cap, and a 2.50% nightly budget on the reference bankroll.",
      "config_signature": "bet_strategy_frontier_v1|favorites|0.030|0.020|0.250|0.750|2.500",
      "optimization_objective": "Static conservative default while matched replay coverage remains limited",
      "optimization_source": "static_fallback",
      "metrics": null
    }
  },
  "strategy_optimization": {
    "method": "Static defaults active until matched replay coverage reaches at least 60 settled games across 20 replay days (current sample: 15 games across 2 days).",
    "risk_free_rate": 0,
    "candidate_count": 0,
    "frontier_point_count": 0,
    "frontier": [],
    "selected": {
      "riskAdjusted": null,
      "aggressive": null,
      "capitalPreservation": null
    }
  },
  "strategies": {
    "riskAdjusted": {
      "summary": {
        "total_final_games": 1039,
        "games_with_forecast": 43,
        "games_with_odds": 15,
        "analyzed_games": 15,
        "suggested_bets": 7,
        "wins": 2,
        "losses": 5,
        "total_risked": 395,
        "total_profit": 190.64999999999998,
        "roi": 0.4826582278481012,
        "starting_bankroll": 5000,
        "current_bankroll": 5190.65,
        "bankroll_start_central": "2026-03-05",
        "coverage_start_central": "2026-03-05",
        "coverage_end_central": "2026-03-07",
        "note": "Replay results use only games with stored pregame forecast and odds snapshots."
      },
      "daily_points": [
        {
          "date_central": "2026-03-05",
          "risked": 200,
          "daily_profit": 385.65,
          "cumulative_profit": 385.65,
          "cumulative_bankroll": 5385.65,
          "bet_count": 4
        },
        {
          "date_central": "2026-03-07",
          "risked": 195,
          "daily_profit": -195,
          "cumulative_profit": 190.64999999999998,
          "cumulative_bankroll": 5190.65,
          "bet_count": 3
        }
      ],
      "bets": [
        {
          "game_id": 401810754,
          "date_central": "2026-03-05",
          "week_start_central": "2026-03-02",
          "start_time_utc": "2026-03-06T00:00Z",
          "final_utc": "2026-03-06T00:00Z",
          "home_team": "ORL",
          "away_team": "DAL",
          "home_score": 115,
          "away_score": 114,
          "forecast_as_of_utc": "2026-03-05T20:00:34+00:00",
          "odds_as_of_utc": "2026-03-05T15:35:17+00:00",
          "odds_snapshot_id": "nba_odds_3a56220d9d6152fa",
          "home_moneyline": -380,
          "away_moneyline": 330,
          "bet_label": "$65 DAL",
          "reason": "Underdog underpriced after uncertainty adjustment",
          "side": "away",
          "team": "DAL",
          "stake": 65,
          "odds": 304,
          "expected_value": 0.20963598130132532,
          "edge": 0.05967469424797836,
          "model_probability": 0.2994148468567637,
          "market_probability": 0.2397401526087853,
          "outcome": "loss",
          "profit": -65,
          "payout": 0,
          "cumulative_profit": -65
        },
        {
          "game_id": 401810757,
          "date_central": "2026-03-05",
          "week_start_central": "2026-03-02",
          "start_time_utc": "2026-03-06T00:30Z",
          "final_utc": "2026-03-06T00:30Z",
          "home_team": "HOU",
          "away_team": "GS",
          "home_score": 113,
          "away_score": 115,
          "forecast_as_of_utc": "2026-03-05T20:00:34+00:00",
          "odds_as_of_utc": "2026-03-05T15:35:17+00:00",
          "odds_snapshot_id": "nba_odds_3a56220d9d6152fa",
          "home_moneyline": -357,
          "away_moneyline": 301,
          "bet_label": "$65 GS",
          "reason": "Underdog underpriced after uncertainty adjustment",
          "side": "away",
          "team": "GS",
          "stake": 65,
          "odds": 301,
          "expected_value": 0.2900364670711164,
          "edge": 0.07832931797446999,
          "model_probability": 0.32170485463120113,
          "market_probability": 0.24337553665673115,
          "outcome": "win",
          "profit": 195.64999999999998,
          "payout": 260.65,
          "cumulative_profit": 130.64999999999998
        },
        {
          "game_id": 401810760,
          "date_central": "2026-03-05",
          "week_start_central": "2026-03-02",
          "start_time_utc": "2026-03-06T02:00Z",
          "final_utc": "2026-03-06T02:00Z",
          "home_team": "PHX",
          "away_team": "CHI",
          "home_score": 103,
          "away_score": 105,
          "forecast_as_of_utc": "2026-03-05T20:00:34+00:00",
          "odds_as_of_utc": "2026-03-05T15:35:17+00:00",
          "odds_snapshot_id": "nba_odds_3a56220d9d6152fa",
          "home_moneyline": -500,
          "away_moneyline": 400,
          "bet_label": "$65 CHI",
          "reason": "Underdog underpriced after uncertainty adjustment",
          "side": "away",
          "team": "CHI",
          "stake": 65,
          "odds": 400,
          "expected_value": 0.33135446904804766,
          "edge": 0.07164002132638808,
          "model_probability": 0.26627089380960955,
          "market_probability": 0.19463087248322147,
          "outcome": "win",
          "profit": 260,
          "payout": 325,
          "cumulative_profit": 390.65
        },
        {
          "game_id": 401810762,
          "date_central": "2026-03-05",
          "week_start_central": "2026-03-02",
          "start_time_utc": "2026-03-06T03:00Z",
          "final_utc": "2026-03-06T03:00Z",
          "home_team": "SAC",
          "away_team": "NO",
          "home_score": 123,
          "away_score": 133,
          "forecast_as_of_utc": "2026-03-05T20:00:34+00:00",
          "odds_as_of_utc": "2026-03-05T15:35:17+00:00",
          "odds_snapshot_id": "nba_odds_3a56220d9d6152fa",
          "home_moneyline": 176,
          "away_moneyline": -195,
          "bet_label": "$5 SAC",
          "reason": "Underdog underpriced after uncertainty adjustment; daily risk cap",
          "side": "home",
          "team": "SAC",
          "stake": 5,
          "odds": 185,
          "expected_value": 0.15288683330599628,
          "edge": 0.06117405641186224,
          "model_probability": 0.4045216958968408,
          "market_probability": 0.34334763948497854,
          "outcome": "loss",
          "profit": -5,
          "payout": 0,
          "cumulative_profit": 385.65
        },
        {
          "game_id": 401810773,
          "date_central": "2026-03-07",
          "week_start_central": "2026-03-02",
          "start_time_utc": "2026-03-08T01:00Z",
          "final_utc": "2026-03-08T01:00Z",
          "home_team": "MEM",
          "away_team": "LAC",
          "home_score": 120,
          "away_score": 123,
          "forecast_as_of_utc": "2026-03-07T11:56:54+00:00",
          "odds_as_of_utc": "2026-03-07T04:52:40+00:00",
          "odds_snapshot_id": "nba_odds_bdc6b30d2ae88076",
          "home_moneyline": 250,
          "away_moneyline": -295,
          "bet_label": "$65 MEM",
          "reason": "Underdog underpriced after uncertainty adjustment",
          "side": "home",
          "team": "MEM",
          "stake": 65,
          "odds": 220,
          "expected_value": 0.7533294093270908,
          "edge": 0.2410562346385426,
          "model_probability": 0.5479154404147158,
          "market_probability": 0.30685920577617326,
          "outcome": "loss",
          "profit": -65,
          "payout": 0,
          "cumulative_profit": 320.65
        },
        {
          "game_id": 401810774,
          "date_central": "2026-03-07",
          "week_start_central": "2026-03-02",
          "start_time_utc": "2026-03-08T01:00Z",
          "final_utc": "2026-03-08T01:00Z",
          "home_team": "MIL",
          "away_team": "UTAH",
          "home_score": 113,
          "away_score": 99,
          "forecast_as_of_utc": "2026-03-07T11:56:54+00:00",
          "odds_as_of_utc": "2026-03-07T04:52:40+00:00",
          "odds_snapshot_id": "nba_odds_bdc6b30d2ae88076",
          "home_moneyline": -460,
          "away_moneyline": 408,
          "bet_label": "$65 UTAH",
          "reason": "Underdog underpriced after uncertainty adjustment",
          "side": "away",
          "team": "UTAH",
          "stake": 65,
          "odds": 390,
          "expected_value": 0.6445677405678978,
          "edge": 0.1363084182197596,
          "model_probability": 0.3356260695036526,
          "market_probability": 0.199317651283893,
          "outcome": "loss",
          "profit": -65,
          "payout": 0,
          "cumulative_profit": 255.64999999999998
        },
        {
          "game_id": 401810775,
          "date_central": "2026-03-07",
          "week_start_central": "2026-03-02",
          "start_time_utc": "2026-03-08T01:30Z",
          "final_utc": "2026-03-08T01:30Z",
          "home_team": "OKC",
          "away_team": "GS",
          "home_score": 104,
          "away_score": 97,
          "forecast_as_of_utc": "2026-03-07T11:56:54+00:00",
          "odds_as_of_utc": "2026-03-07T04:52:40+00:00",
          "odds_snapshot_id": "nba_odds_bdc6b30d2ae88076",
          "home_moneyline": -769,
          "away_moneyline": 600,
          "bet_label": "$65 GS",
          "reason": "Underdog underpriced after uncertainty adjustment",
          "side": "away",
          "team": "GS",
          "stake": 65,
          "odds": 600,
          "expected_value": 0.9813335076568399,
          "edge": 0.14370338165589516,
          "model_probability": 0.28304764395097715,
          "market_probability": 0.13934426229508198,
          "outcome": "loss",
          "profit": -65,
          "payout": 0,
          "cumulative_profit": 190.64999999999998
        }
      ]
    },
    "aggressive": {
      "summary": {
        "total_final_games": 1039,
        "games_with_forecast": 43,
        "games_with_odds": 15,
        "analyzed_games": 15,
        "suggested_bets": 7,
        "wins": 2,
        "losses": 5,
        "total_risked": 570,
        "total_profit": 240.89999999999998,
        "roi": 0.42263157894736836,
        "starting_bankroll": 5000,
        "current_bankroll": 5240.9,
        "bankroll_start_central": "2026-03-05",
        "coverage_start_central": "2026-03-05",
        "coverage_end_central": "2026-03-07",
        "note": "Replay results use only games with stored pregame forecast and odds snapshots."
      },
      "daily_points": [
        {
          "date_central": "2026-03-05",
          "risked": 300,
          "daily_profit": 510.9,
          "cumulative_profit": 510.9,
          "cumulative_bankroll": 5510.9,
          "bet_count": 4
        },
        {
          "date_central": "2026-03-07",
          "risked": 270,
          "daily_profit": -270,
          "cumulative_profit": 240.89999999999998,
          "cumulative_bankroll": 5240.9,
          "bet_count": 3
        }
      ],
      "bets": [
        {
          "game_id": 401810754,
          "date_central": "2026-03-05",
          "week_start_central": "2026-03-02",
          "start_time_utc": "2026-03-06T00:00Z",
          "final_utc": "2026-03-06T00:00Z",
          "home_team": "ORL",
          "away_team": "DAL",
          "home_score": 115,
          "away_score": 114,
          "forecast_as_of_utc": "2026-03-05T20:00:34+00:00",
          "odds_as_of_utc": "2026-03-05T15:35:17+00:00",
          "odds_snapshot_id": "nba_odds_3a56220d9d6152fa",
          "home_moneyline": -380,
          "away_moneyline": 330,
          "bet_label": "$90 DAL",
          "reason": "Underdog underpriced after uncertainty adjustment",
          "side": "away",
          "team": "DAL",
          "stake": 90,
          "odds": 304,
          "expected_value": 0.20963598130132532,
          "edge": 0.05967469424797836,
          "model_probability": 0.2994148468567637,
          "market_probability": 0.2397401526087853,
          "outcome": "loss",
          "profit": -90,
          "payout": 0,
          "cumulative_profit": -90
        },
        {
          "game_id": 401810757,
          "date_central": "2026-03-05",
          "week_start_central": "2026-03-02",
          "start_time_utc": "2026-03-06T00:30Z",
          "final_utc": "2026-03-06T00:30Z",
          "home_team": "HOU",
          "away_team": "GS",
          "home_score": 113,
          "away_score": 115,
          "forecast_as_of_utc": "2026-03-05T20:00:34+00:00",
          "odds_as_of_utc": "2026-03-05T15:35:17+00:00",
          "odds_snapshot_id": "nba_odds_3a56220d9d6152fa",
          "home_moneyline": -357,
          "away_moneyline": 301,
          "bet_label": "$90 GS",
          "reason": "Underdog underpriced after uncertainty adjustment",
          "side": "away",
          "team": "GS",
          "stake": 90,
          "odds": 301,
          "expected_value": 0.2900364670711164,
          "edge": 0.07832931797446999,
          "model_probability": 0.32170485463120113,
          "market_probability": 0.24337553665673115,
          "outcome": "win",
          "profit": 270.9,
          "payout": 360.9,
          "cumulative_profit": 180.89999999999998
        },
        {
          "game_id": 401810760,
          "date_central": "2026-03-05",
          "week_start_central": "2026-03-02",
          "start_time_utc": "2026-03-06T02:00Z",
          "final_utc": "2026-03-06T02:00Z",
          "home_team": "PHX",
          "away_team": "CHI",
          "home_score": 103,
          "away_score": 105,
          "forecast_as_of_utc": "2026-03-05T20:00:34+00:00",
          "odds_as_of_utc": "2026-03-05T15:35:17+00:00",
          "odds_snapshot_id": "nba_odds_3a56220d9d6152fa",
          "home_moneyline": -500,
          "away_moneyline": 400,
          "bet_label": "$90 CHI",
          "reason": "Underdog underpriced after uncertainty adjustment",
          "side": "away",
          "team": "CHI",
          "stake": 90,
          "odds": 400,
          "expected_value": 0.33135446904804766,
          "edge": 0.07164002132638808,
          "model_probability": 0.26627089380960955,
          "market_probability": 0.19463087248322147,
          "outcome": "win",
          "profit": 360,
          "payout": 450,
          "cumulative_profit": 540.9
        },
        {
          "game_id": 401810762,
          "date_central": "2026-03-05",
          "week_start_central": "2026-03-02",
          "start_time_utc": "2026-03-06T03:00Z",
          "final_utc": "2026-03-06T03:00Z",
          "home_team": "SAC",
          "away_team": "NO",
          "home_score": 123,
          "away_score": 133,
          "forecast_as_of_utc": "2026-03-05T20:00:34+00:00",
          "odds_as_of_utc": "2026-03-05T15:35:17+00:00",
          "odds_snapshot_id": "nba_odds_3a56220d9d6152fa",
          "home_moneyline": 176,
          "away_moneyline": -195,
          "bet_label": "$30 SAC",
          "reason": "Underdog underpriced after uncertainty adjustment; daily risk cap",
          "side": "home",
          "team": "SAC",
          "stake": 30,
          "odds": 185,
          "expected_value": 0.15288683330599628,
          "edge": 0.06117405641186224,
          "model_probability": 0.4045216958968408,
          "market_probability": 0.34334763948497854,
          "outcome": "loss",
          "profit": -30,
          "payout": 0,
          "cumulative_profit": 510.9
        },
        {
          "game_id": 401810773,
          "date_central": "2026-03-07",
          "week_start_central": "2026-03-02",
          "start_time_utc": "2026-03-08T01:00Z",
          "final_utc": "2026-03-08T01:00Z",
          "home_team": "MEM",
          "away_team": "LAC",
          "home_score": 120,
          "away_score": 123,
          "forecast_as_of_utc": "2026-03-07T11:56:54+00:00",
          "odds_as_of_utc": "2026-03-07T04:52:40+00:00",
          "odds_snapshot_id": "nba_odds_bdc6b30d2ae88076",
          "home_moneyline": 250,
          "away_moneyline": -295,
          "bet_label": "$90 MEM",
          "reason": "Underdog underpriced after uncertainty adjustment",
          "side": "home",
          "team": "MEM",
          "stake": 90,
          "odds": 220,
          "expected_value": 0.7533294093270908,
          "edge": 0.2410562346385426,
          "model_probability": 0.5479154404147158,
          "market_probability": 0.30685920577617326,
          "outcome": "loss",
          "profit": -90,
          "payout": 0,
          "cumulative_profit": 420.9
        },
        {
          "game_id": 401810774,
          "date_central": "2026-03-07",
          "week_start_central": "2026-03-02",
          "start_time_utc": "2026-03-08T01:00Z",
          "final_utc": "2026-03-08T01:00Z",
          "home_team": "MIL",
          "away_team": "UTAH",
          "home_score": 113,
          "away_score": 99,
          "forecast_as_of_utc": "2026-03-07T11:56:54+00:00",
          "odds_as_of_utc": "2026-03-07T04:52:40+00:00",
          "odds_snapshot_id": "nba_odds_bdc6b30d2ae88076",
          "home_moneyline": -460,
          "away_moneyline": 408,
          "bet_label": "$90 UTAH",
          "reason": "Underdog underpriced after uncertainty adjustment",
          "side": "away",
          "team": "UTAH",
          "stake": 90,
          "odds": 390,
          "expected_value": 0.6445677405678978,
          "edge": 0.1363084182197596,
          "model_probability": 0.3356260695036526,
          "market_probability": 0.199317651283893,
          "outcome": "loss",
          "profit": -90,
          "payout": 0,
          "cumulative_profit": 330.9
        },
        {
          "game_id": 401810775,
          "date_central": "2026-03-07",
          "week_start_central": "2026-03-02",
          "start_time_utc": "2026-03-08T01:30Z",
          "final_utc": "2026-03-08T01:30Z",
          "home_team": "OKC",
          "away_team": "GS",
          "home_score": 104,
          "away_score": 97,
          "forecast_as_of_utc": "2026-03-07T11:56:54+00:00",
          "odds_as_of_utc": "2026-03-07T04:52:40+00:00",
          "odds_snapshot_id": "nba_odds_bdc6b30d2ae88076",
          "home_moneyline": -769,
          "away_moneyline": 600,
          "bet_label": "$90 GS",
          "reason": "Underdog underpriced after uncertainty adjustment",
          "side": "away",
          "team": "GS",
          "stake": 90,
          "odds": 600,
          "expected_value": 0.9813335076568399,
          "edge": 0.14370338165589516,
          "model_probability": 0.28304764395097715,
          "market_probability": 0.13934426229508198,
          "outcome": "loss",
          "profit": -90,
          "payout": 0,
          "cumulative_profit": 240.89999999999998
        }
      ]
    },
    "capitalPreservation": {
      "summary": {
        "total_final_games": 1039,
        "games_with_forecast": 43,
        "games_with_odds": 15,
        "analyzed_games": 15,
        "suggested_bets": 2,
        "wins": 2,
        "losses": 0,
        "total_risked": 80,
        "total_profit": 42.13444213444213,
        "roi": 0.5266805266805267,
        "starting_bankroll": 5000,
        "current_bankroll": 5042.134442134442,
        "bankroll_start_central": "2026-03-05",
        "coverage_start_central": "2026-03-05",
        "coverage_end_central": "2026-03-07",
        "note": "Replay results use only games with stored pregame forecast and odds snapshots."
      },
      "daily_points": [
        {
          "date_central": "2026-03-05",
          "risked": 80,
          "daily_profit": 42.13444213444213,
          "cumulative_profit": 42.13444213444213,
          "cumulative_bankroll": 5042.134442134442,
          "bet_count": 2
        }
      ],
      "bets": [
        {
          "game_id": 401810758,
          "date_central": "2026-03-05",
          "week_start_central": "2026-03-02",
          "start_time_utc": "2026-03-06T01:00Z",
          "final_utc": "2026-03-06T01:00Z",
          "home_team": "MIN",
          "away_team": "TOR",
          "home_score": 115,
          "away_score": 107,
          "forecast_as_of_utc": "2026-03-05T20:00:34+00:00",
          "odds_as_of_utc": "2026-03-05T15:35:17+00:00",
          "odds_snapshot_id": "nba_odds_3a56220d9d6152fa",
          "home_moneyline": -228,
          "away_moneyline": 198,
          "bet_label": "$40 MIN",
          "reason": "Favorite underpriced after uncertainty adjustment",
          "side": "home",
          "team": "MIN",
          "stake": 40,
          "odds": -195,
          "expected_value": 0.05080720691070395,
          "edge": 0.04618947965523201,
          "model_probability": 0.6946013740596179,
          "market_probability": 0.6484118944043858,
          "outcome": "win",
          "profit": 20.51282051282051,
          "payout": 60.51282051282051,
          "cumulative_profit": 20.51282051282051
        },
        {
          "game_id": 401810761,
          "date_central": "2026-03-05",
          "week_start_central": "2026-03-02",
          "start_time_utc": "2026-03-06T03:00Z",
          "final_utc": "2026-03-06T03:00Z",
          "home_team": "DEN",
          "away_team": "LAL",
          "home_score": 120,
          "away_score": 113,
          "forecast_as_of_utc": "2026-03-05T20:00:34+00:00",
          "odds_as_of_utc": "2026-03-05T15:35:17+00:00",
          "odds_snapshot_id": "nba_odds_3a56220d9d6152fa",
          "home_moneyline": -185,
          "away_moneyline": 170,
          "bet_label": "$40 DEN",
          "reason": "Favorite underpriced after uncertainty adjustment",
          "side": "home",
          "team": "DEN",
          "stake": 40,
          "odds": -185,
          "expected_value": 0.050106517917386295,
          "edge": 0.04493680950720691,
          "model_probability": 0.6816480905779525,
          "market_probability": 0.6367112810707456,
          "outcome": "win",
          "profit": 21.62162162162162,
          "payout": 61.62162162162162,
          "cumulative_profit": 42.13444213444213
        }
      ]
    }
  }
}
